promptadmin/__init__.py
promptadmin/output/__init__.py
promptadmin/output/parser_output_service.py
promptadmin/prompt_service/__init__.py
promptadmin/prompt_service/decorator.py
promptadmin/prompt_service/inspect_prompt_service.py
promptadmin/prompt_service/models/__init__.py
promptadmin/prompt_service/models/abstract_streamer.py
promptadmin/prompt_service/models/anthropic.py
promptadmin/prompt_service/models/anthropic_bedrok.py
promptadmin/prompt_service/models/base_model_service.py
promptadmin/prompt_service/models/openai_model.py
promptadmin/sync/__init__.py
promptadmin/sync/collector.py
promptadmin/sync/router.py
promptadmin/sync/status_monitor/__init__.py
promptadmin/sync/status_monitor/test_load_service.py
promptadmin/sync/status_monitor/test_run_job.py
promptadmin/sync/status_monitor/test_run_service.py
promptadmin/types/__init__.py
promptadmin/types/message.py
promptadmin/types/model_response.py
promptadmin/types/model_service_info.py
promptadmin/types/project_promt_info.py
promptadmin/types/prompt_service_info.py
promptadmin/types/settings.py
promptadmin/vars/__init__.py
promptadmin/vars/var_service.py
prompt_admin-0.1.24.dist-info/METADATA
prompt_admin-0.1.24.dist-info/WHEEL
prompt_admin-0.1.24.dist-info/RECORD
