Metadata-Version: 2.1
Name: prompt-admin
Version: 0.1.24
Summary: 
Author: phoenix
Author-email: vova24848@gmail.com
Requires-Python: >=3.11,<4.0
Classifier: Programming Language :: Python :: 3
Classifier: Programming Language :: Python :: 3.11
Classifier: Programming Language :: Python :: 3.12
Requires-Dist: Jinja2 (>=3.1.2,<4.0.0)
Requires-Dist: SQLAlchemy (>=2.0.23,<3.0.0)
Requires-Dist: anthropic (>=0.34.2,<0.35.0)
Requires-Dist: asyncpg (>=0.29.0,<0.30.0)
Requires-Dist: boto3 (>=1.35.24,<2.0.0)
Requires-Dist: datamodel-code-generator (>=0.26.0,<0.27.0)
Requires-Dist: fastapi (>=0.110.1,<0.111.0)
Requires-Dist: openai (>=1.48.0,<2.0.0)
Requires-Dist: polyfactory (>=2.16.2,<3.0.0)
Requires-Dist: pydantic (>=2.8.2,<3.0.0)
Requires-Dist: pytest (>=7.4.3,<8.0.0)
Requires-Dist: pytest-asyncio (>=0.21.1,<0.22.0)
Requires-Dist: pytest-json-report (>=1.5.0,<2.0.0)
Requires-Dist: sqlmodel (>=0.0.21,<0.0.22)
Requires-Dist: xmltodict (>=0.13.0,<0.14.0)
